mysql_mcp_server_pro/__init__.py
mysql_mcp_server_pro/cli.py
mysql_mcp_server_pro/server.py
mysql_mcp_server_pro/config/__init__.py
mysql_mcp_server_pro/config/dbconfig.py
mysql_mcp_server_pro/handles/__init__.py
mysql_mcp_server_pro/handles/base.py
mysql_mcp_server_pro/handles/execute_sql.py
mysql_mcp_server_pro/handles/get_chinese_initials.py
mysql_mcp_server_pro/handles/get_db_health_index_usage.py
mysql_mcp_server_pro/handles/get_db_health_running.py
mysql_mcp_server_pro/handles/get_table_desc.py
mysql_mcp_server_pro/handles/get_table_index.py
mysql_mcp_server_pro/handles/get_table_lock.py
mysql_mcp_server_pro/handles/get_table_name.py
mysql_mcp_server_pro/prompts/AnalysisMySqlIssues.py
mysql_mcp_server_pro/prompts/BasePrompt.py
mysql_mcp_server_pro/prompts/QueryTableData.py
mysql_mcp_server_pro/prompts/__init__.py
mcp_mysql_airnet-0.0.1.dist-info/METADATA
mcp_mysql_airnet-0.0.1.dist-info/WHEEL
mcp_mysql_airnet-0.0.1.dist-info/entry_points.txt
mcp_mysql_airnet-0.0.1.dist-info/licenses/LICENSE
mcp_mysql_airnet-0.0.1.dist-info/RECORD
