Metadata-Version: 2.4
Name: mcp_mysql_AirNet
Version: 0.0.1
Summary: Use for AirNet:Support for SSE, STDIO in MySQL MCP server, includes CRUD, database anomaly analysis capabilities .支持SSE，STDIO；包含了数据库异常分析能力；且便于开发者们进行个性化的工具扩展
Author: atmas
License: MIT
License-File: LICENSE
Requires-Python: >=3.11
Requires-Dist: mcp>=1.8.0
Requires-Dist: mysql-connector-python>=9.2.0
Requires-Dist: pypinyin>=0.54.0
Requires-Dist: python-dotenv>=1.1.0
Requires-Dist: starlette>=0.46.1
Requires-Dist: uvicorn>=0.34.0
